multi_agent_ale_py/ale_c_wrapper.h
multi_agent_ale_py/ale_python_interface.py
multi_agent_ale_py/__init__.py
multi_agent_ale_py/libale_c.so
multi_agent_ale_py/ale_c_wrapper.cpp
multi_agent_ale_py/tests/fixtures/tetris.bin
multi_agent_ale_py.libs/libz-eb09ad1d.so.1.2.3
multi_agent_ale_py-0.1.11.dist-info/RECORD
multi_agent_ale_py-0.1.11.dist-info/METADATA
multi_agent_ale_py-0.1.11.dist-info/top_level.txt
multi_agent_ale_py-0.1.11.dist-info/WHEEL
multi_agent_ale_py-0.1.11.dist-info/LICENSE.md
