Metadata-Version: 2.1
Name: multi-agent-ale-py
Version: 0.1.11
Summary: Multi-Agent Arcade Learning Environment Python Interface
Home-page: https://github.com/PettingZoo-Team/Multi-Agent-ALE
Author: PettingZoo Team
Author-email: justinkterry@gmail.com
License: GPL
Keywords: reinforcement-learning,arcade-learning-environment,atari
Platform: UNKNOWN
Classifier: Development Status :: 5 - Production/Stable
Classifier: Topic :: Scientific/Engineering :: Artificial Intelligence
Classifier: Intended Audience :: Science/Research
Classifier: Programming Language :: Python :: 3
Classifier: Programming Language :: Python :: 3.5
Classifier: Programming Language :: Python :: 3.6
Classifier: Programming Language :: Python :: 3.7
Classifier: Programming Language :: Python :: 3.8
Requires-Dist: numpy
